{
  "$schema": "https://developer.microsoft.com/json-schemas/fabric/item/report/definition/visualContainer/2.9.0/schema.json",
  "name": "225a52d05304b29210d1",
  "position": {
    "x": 0,
    "y": 300,
    "z": 0,
    "height": 780,
    "width": 960,
    "tabOrder": 0
  },
  "visual": {
    "visualType": "filledMap",
    "query": {
      "queryState": {
        "Category": {
          "projections": [
            {
              "field": {
                "Column": {
                  "Expression": {
                    "SourceRef": {
                      "Entity": "powerbi_geographic_summary"
                    }
                  },
                  "Property": "map_location_country"
                }
              },
              "queryRef": "powerbi_geographic_summary.map_location_country",
              "nativeQueryRef": "map_location_country",
              "active": true
            },
            {
              "field": {
                "Column": {
                  "Expression": {
                    "SourceRef": {
                      "Entity": "powerbi_geographic_summary"
                    }
                  },
                  "Property": "map_location_state"
                }
              },
              "queryRef": "powerbi_geographic_summary.map_location_state",
              "nativeQueryRef": "map_location_state",
              "active": false
            }
          ]
        },
        "Series": {
          "projections": [
            {
              "field": {
                "Column": {
                  "Expression": {
                    "SourceRef": {
                      "Entity": "powerbi_geographic_summary"
                    }
                  },
                  "Property": "map_location_region"
                }
              },
              "queryRef": "powerbi_geographic_summary.map_location_region",
              "nativeQueryRef": "map_location_region"
            }
          ]
        },
        "Tooltips": {
          "projections": [
            {
              "field": {
                "Aggregation": {
                  "Expression": {
                    "Column": {
                      "Expression": {
                        "SourceRef": {
                          "Entity": "powerbi_geographic_summary"
                        }
                      },
                      "Property": "high_risk_order_count"
                    }
                  },
                  "Function": 0
                }
              },
              "queryRef": "Sum(powerbi_geographic_summary.high_risk_order_count)",
              "nativeQueryRef": "Sum of high_risk_order_count"
            }
          ]
        }
      }
    },
    "objects": {
      "mapStyles": [
        {
          "properties": {
            "mapTheme": {
              "expr": {
                "Literal": {
                  "Value": "'canvasDark'"
                }
              }
            }
          }
        }
      ],
      "mapControls": [
        {
          "properties": {
            "autoZoom": {
              "expr": {
                "Literal": {
                  "Value": "true"
                }
              }
            },
            "showZoomButtons": {
              "expr": {
                "Literal": {
                  "Value": "false"
                }
              }
            },
            "showLassoButton": {
              "expr": {
                "Literal": {
                  "Value": "false"
                }
              }
            },
            "geocodingCulture": {
              "expr": {
                "Literal": {
                  "Value": "''"
                }
              }
            }
          }
        }
      ],
      "legend": [
        {
          "properties": {
            "show": {
              "expr": {
                "Literal": {
                  "Value": "false"
                }
              }
            }
          }
        }
      ],
      "dataPoint": [
        {
          "properties": {
            "fillRule": {
              "linearGradient2": {
                "min": {
                  "color": {
                    "expr": {
                      "Literal": {
                        "Value": "'minColor'"
                      }
                    }
                  }
                },
                "max": {
                  "color": {
                    "expr": {
                      "Literal": {
                        "Value": "'maxColor'"
                      }
                    }
                  }
                },
                "nullColoringStrategy": {
                  "strategy": {
                    "expr": {
                      "Literal": {
                        "Value": "'asZero'"
                      }
                    }
                  }
                }
              }
            }
          }
        }
      ]
    },
    "visualContainerObjects": {
      "border": [
        {
          "properties": {
            "radius": {
              "expr": {
                "Literal": {
                  "Value": "30D"
                }
              }
            },
            "width": {
              "expr": {
                "Literal": {
                  "Value": "2D"
                }
              }
            }
          }
        }
      ],
      "background": [
        {
          "properties": {
            "transparency": {
              "expr": {
                "Literal": {
                  "Value": "26D"
                }
              }
            }
          }
        }
      ],
      "title": [
        {
          "properties": {
            "text": {
              "expr": {
                "Literal": {
                  "Value": "'High-Risk Order Exposure by Geography'"
                }
              }
            }
          }
        }
      ],
      "subTitle": [
        {
          "properties": {
            "show": {
              "expr": {
                "Literal": {
                  "Value": "true"
                }
              }
            },
            "text": {
              "expr": {
                "Literal": {
                  "Value": "'Countries and regions with concentrated high-risk order volume.'"
                }
              }
            },
            "fontSize": {
              "expr": {
                "Literal": {
                  "Value": "12D"
                }
              }
            },
            "fontColor": {
              "solid": {
                "color": {
                  "expr": {
                    "ThemeDataColor": {
                      "ColorId": 0,
                      "Percent": -0.2
                    }
                  }
                }
              }
            }
          }
        }
      ]
    },
    "drillFilterOtherVisuals": true
  },
  "filterConfig": {
    "filters": [
      {
        "name": "5dd7aa0f39d19c8c4b04",
        "field": {
          "Column": {
            "Expression": {
              "SourceRef": {
                "Entity": "powerbi_geographic_summary"
              }
            },
            "Property": "map_location_country"
          }
        },
        "type": "TopN",
        "filter": {
          "Version": 2,
          "From": [
            {
              "Name": "subquery",
              "Expression": {
                "Subquery": {
                  "Query": {
                    "Version": 2,
                    "From": [
                      {
                        "Name": "p",
                        "Entity": "powerbi_geographic_summary",
                        "Type": 0
                      },
                      {
                        "Name": "d",
                        "Entity": "Dashboard_Measures",
                        "Type": 0
                      }
                    ],
                    "Select": [
                      {
                        "Column": {
                          "Expression": {
                            "SourceRef": {
                              "Source": "p"
                            }
                          },
                          "Property": "map_location_country"
                        },
                        "Name": "field"
                      }
                    ],
                    "OrderBy": [
                      {
                        "Direction": 2,
                        "Expression": {
                          "Measure": {
                            "Expression": {
                              "SourceRef": {
                                "Source": "d"
                              }
                            },
                            "Property": "Geo Order Value"
                          }
                        }
                      }
                    ],
                    "Top": 10
                  }
                }
              },
              "Type": 2
            },
            {
              "Name": "p",
              "Entity": "powerbi_geographic_summary",
              "Type": 0
            }
          ],
          "Where": [
            {
              "Condition": {
                "In": {
                  "Expressions": [
                    {
                      "Column": {
                        "Expression": {
                          "SourceRef": {
                            "Source": "p"
                          }
                        },
                        "Property": "map_location_country"
                      }
                    }
                  ],
                  "Table": {
                    "SourceRef": {
                      "Source": "subquery"
                    }
                  }
                }
              }
            }
          ]
        }
      },
      {
        "name": "5b10ed039185720ed400",
        "field": {
          "Column": {
            "Expression": {
              "SourceRef": {
                "Entity": "powerbi_geographic_summary"
              }
            },
            "Property": "map_location_region"
          }
        },
        "type": "Categorical"
      },
      {
        "name": "5bf8aee2467071500b1b",
        "field": {
          "Column": {
            "Expression": {
              "SourceRef": {
                "Entity": "powerbi_geographic_summary"
              }
            },
            "Property": "map_location_state"
          }
        },
        "type": "Categorical"
      },
      {
        "name": "0ef32042759ae880cc08",
        "field": {
          "Aggregation": {
            "Expression": {
              "Column": {
                "Expression": {
                  "SourceRef": {
                    "Entity": "powerbi_geographic_summary"
                  }
                },
                "Property": "high_risk_order_count"
              }
            },
            "Function": 0
          }
        },
        "type": "Advanced"
      }
    ]
  }
}